{"version": 0.6, "generator": "Overpass API 0.7.60 f4c14d41", "osm3s": {"timestamp_osm_base": "2023-05-02T21:21:23Z", "copyright": "The data included in this document is from www.openstreetmap.org. The data is made available under ODbL."}, "elements": [{"type": "node", "id": 334107323, "lat": -33.7617681, "lon": 150.8592257, "tags": {"name": "The Nurragingy Blacksmith", "tourism": "attraction"}}, {"type": "node", "id": 465200731, "lat": -33.6041427, "lon": 150.8225468, "tags": {"name": "Doctors House", "tourism": "attraction"}}, {"type": "node", "id": 465200755, "lat": -33.6088255, "lon": 150.8131398, "tags": {"name": "Anglican Rectory (1825)", "tourism": "attraction"}}, {"type": "node", "id": 465200757, "lat": -33.6133162, "lon": 150.811954, "tags": {"name": "Old Station Masters House \u2013 1880", "tourism": "attraction"}}, {"type": "node", "id": 670333770, "lat": -33.7621413, "lon": 150.6391466, "tags": {"name": "Zig Zag Railway", "tourism": "attraction"}}, {"type": "node", "id": 670333771, "lat": -33.7611214, "lon": 150.6390688, "tags": {"historic": "railway_station", "name": "Lucasville Station", "tourism": "attraction"}}, {"type": "node", "id": 1850042684, "lat": -33.5710737, "lon": 150.8380204}, {"type": "node", "id": 1851292347, "lat": -33.5709254, "lon": 150.8367163}, {"type": "node", "id": 1851292349, "lat": -33.5709566, "lon": 150.8369266}, {"type": "node", "id": 1851292351, "lat": -33.5710481, "lon": 150.8370692}, {"type": "node", "id": 1851292353, "lat": -33.5710617, "lon": 150.8365832}, {"type": "node", "id": 1851292355, "lat": -33.571161, "lon": 150.8370692}, {"type": "node", "id": 1851292359, "lat": -33.5712389, "lon": 150.836978}, {"type": "node", "id": 1851292360, "lat": -33.5712778, "lon": 150.8365177}, {"type": "node", "id": 1851292364, "lat": -33.5712875, "lon": 150.8369009}, {"type": "node", "id": 1851292366, "lat": -33.5713031, "lon": 150.8360972}, {"type": "node", "id": 1851292368, "lat": -33.5713226, "lon": 150.835985}, {"type": "node", "id": 1851292370, "lat": -33.5713343, "lon": 150.8368075}, {"type": "node", "id": 1851292372, "lat": -33.5713382, "lon": 150.8361836}, {"type": "node", "id": 1851292373, "lat": -33.5714024, "lon": 150.836242}, {"type": "node", "id": 1851292375, "lat": -33.5714258, "lon": 150.8368051}, {"type": "node", "id": 1851292387, "lat": -33.5714394, "lon": 150.8358612}, {"type": "node", "id": 1851292388, "lat": -33.5714511, "lon": 150.8368215}, {"type": "node", "id": 1851292389, "lat": -33.5714686, "lon": 150.8362374}, {"type": "node", "id": 1851292390, "lat": -33.5714861, "lon": 150.8369477}, {"type": "node", "id": 1851292391, "lat": -33.5715212, "lon": 150.8370341}, {"type": "node", "id": 1851292392, "lat": -33.5715309, "lon": 150.8361626}, {"type": "node", "id": 1851292393, "lat": -33.5715328, "lon": 150.8364547}, {"type": "node", "id": 1851292394, "lat": -33.5715523, "lon": 150.8360458}, {"type": "node", "id": 1851292396, "lat": -33.5716049, "lon": 150.8358986}, {"type": "node", "id": 1851292398, "lat": -33.5716185, "lon": 150.8356369}, {"type": "node", "id": 1851292400, "lat": -33.5716204, "lon": 150.8370879}, {"type": "node", "id": 1851292402, "lat": -33.5717003, "lon": 150.8367093}, {"type": "node", "id": 1851292404, "lat": -33.5717081, "lon": 150.8366089}, {"type": "node", "id": 1851292410, "lat": -33.5717353, "lon": 150.8371439}, {"type": "node", "id": 1851292412, "lat": -33.571745, "lon": 150.8368145}, {"type": "node", "id": 1851292414, "lat": -33.5717665, "lon": 150.8363962}, {"type": "node", "id": 1851292416, "lat": -33.5717957, "lon": 150.8365458}, {"type": "node", "id": 1851292418, "lat": -33.5717995, "lon": 150.8354383}, {"type": "node", "id": 1851292425, "lat": -33.5718151, "lon": 150.8358939}, {"type": "node", "id": 1851292426, "lat": -33.5718326, "lon": 150.8368706}, {"type": "node", "id": 1851292427, "lat": -33.5718735, "lon": 150.8372047}, {"type": "node", "id": 1851292428, "lat": -33.5718794, "lon": 150.8363028}, {"type": "node", "id": 1851292429, "lat": -33.5718852, "lon": 150.8361275}, {"type": "node", "id": 1851292435, "lat": -33.5719164, "lon": 150.8354686}, {"type": "node", "id": 1851292437, "lat": -33.5719183, "lon": 150.8365832}, {"type": "node", "id": 1851292441, "lat": -33.5719981, "lon": 150.837228}, {"type": "node", "id": 1851292443, "lat": -33.5720079, "lon": 150.8366953}, {"type": "node", "id": 1851292445, "lat": -33.5720176, "lon": 150.836978}, {"type": "node", "id": 1851292447, "lat": -33.5720273, "lon": 150.8355528}, {"type": "node", "id": 1851292449, "lat": -33.5720702, "lon": 150.8368075}, {"type": "node", "id": 1851292451, "lat": -33.5720994, "lon": 150.8370458}, {"type": "node", "id": 1851292457, "lat": -33.5721071, "lon": 150.837179}, {"type": "node", "id": 1851292459, "lat": -33.572111, "lon": 150.8357373}, {"type": "node", "id": 1851292461, "lat": -33.5721286, "lon": 150.8370995}, {"type": "node", "id": 1851292466, "lat": -33.5721597, "lon": 150.8368402}, {"type": "node", "id": 1851292468, "lat": -33.572185, "lon": 150.8361018}, {"type": "node", "id": 1851292470, "lat": -33.5722531, "lon": 150.8365691}, {"type": "node", "id": 1851292472, "lat": -33.572257, "lon": 150.8367467}, {"type": "node", "id": 3111982183, "lat": -33.3676009, "lon": 150.9867545, "tags": {"name": "Hangman's Rock", "natural": "rock", "source": "survey", "tourism": "attraction"}}, {"type": "node", "id": 3979252646, "lat": -33.727095, "lon": 150.6881203, "tags": {"addr:city": "Castlereagh", "addr:housenumber": "Gate D", "addr:postcode": "2749", "addr:street": "Old Castlereagh Road", "name": "Jetpack Adventures", "operator": "1800Jetpack", "phone:AU": "1800 538 722", "source": "Lodal Knowledge,Website", "tourism": "attraction", "website": "https://www.jetpackadventures.com.au/sydney/"}}, {"type": "node", "id": 4374907570, "lat": -33.5637017, "lon": 150.8725345, "tags": {"name": "Waterski Park", "source": "NSW LPI Base Map", "source:date": "2016-08", "tourism": "attraction"}}, {"type": "node", "id": 4374907578, "lat": -33.6119208, "lon": 150.6928203, "tags": {"name": "tree top walk", "source": "NSW LPI Base Map", "source:date": "2016-08", "tourism": "attraction"}}, {"type": "node", "id": 4609148885, "lat": -33.568417, "lon": 150.8368845}, {"type": "node", "id": 4609152289, "lat": -33.5692931, "lon": 150.8377482}, {"type": "node", "id": 4609152291, "lat": -33.5696909, "lon": 150.8382954}, {"type": "node", "id": 4609152294, "lat": -33.57012, "lon": 150.8386977}, {"type": "node", "id": 4609152297, "lat": -33.5703926, "lon": 150.8351733}, {"type": "node", "id": 4609152299, "lat": -33.5707279, "lon": 150.8350123}, {"type": "node", "id": 4609152303, "lat": -33.5716397, "lon": 150.8348568}, {"type": "node", "id": 4609152306, "lat": -33.5721045, "lon": 150.8350499}, {"type": "node", "id": 4609152308, "lat": -33.5725336, "lon": 150.8350445}, {"type": "node", "id": 5108458122, "lat": -33.7588536, "lon": 150.6875381, "tags": {"name": "Penrith Panthers Rugby League", "tourism": "attraction"}}, {"type": "node", "id": 5415532122, "lat": -33.6032268, "lon": 150.8236552, "tags": {"name": "Paddlewheeler", "tourism": "attraction"}}, {"type": "node", "id": 5664538444, "lat": -33.570289, "lon": 150.8384101}, {"type": "node", "id": 5664538445, "lat": -33.5704636, "lon": 150.8382226}, {"type": "node", "id": 5664538446, "lat": -33.5709465, "lon": 150.8379911}, {"type": "node", "id": 5664538447, "lat": -33.5710169, "lon": 150.8380063}, {"type": "node", "id": 5664538448, "lat": -33.5712449, "lon": 150.8379133}, {"type": "node", "id": 5664538449, "lat": -33.5716701, "lon": 150.8377156}, {"type": "node", "id": 5664538450, "lat": -33.571763, "lon": 150.8377258}, {"type": "node", "id": 5664538451, "lat": -33.5719165, "lon": 150.837621}, {"type": "node", "id": 5664538452, "lat": -33.5720319, "lon": 150.8376193}, {"type": "node", "id": 5664538453, "lat": -33.5720573, "lon": 150.8376734}, {"type": "node", "id": 5664538527, "lat": -33.5703898, "lon": 150.8382994}, {"type": "node", "id": 5664538528, "lat": -33.5706494, "lon": 150.8381144}, {"type": "node", "id": 5664538529, "lat": -33.5718067, "lon": 150.8377039}, {"type": "node", "id": 5664538530, "lat": -33.5722134, "lon": 150.8376771}, {"type": "node", "id": 5664538531, "lat": -33.572933, "lon": 150.8374733}, {"type": "way", "id": 174440305, "nodes": [1851292353, 1851292360, 1851292393, 1851292414, 1851292428, 1851292429, 1851292425, 1851292396, 1851292394, 1851292392, 1851292389, 1851292373, 1851292372, 1851292366, 1851292368, 1851292387, 1851292398, 1851292418, 1851292435, 1851292447, 1851292459, 1851292468, 1851292470, 1851292472, 1851292466, 1851292449, 1851292443, 1851292437, 1851292416, 1851292404, 1851292402, 1851292412, 1851292426, 1851292445, 1851292451, 1851292461, 1851292457, 1851292441, 1851292427, 1851292410, 1851292400, 1851292391, 1851292390, 1851292388, 1851292375, 1851292370, 1851292364, 1851292359, 1851292355, 1851292351, 1851292349, 1851292347, 1851292353], "tags": {"leisure": "track", "name": "Indy 800 Kart Track", "source": "NSW LPI Base Map", "source:date": "2016-08", "sport": "karting", "tourism": "attraction", "website": "http://www.indy800.com.au/indy800/"}}, {"type": "way", "id": 466011022, "nodes": [4609152294, 5664538444, 5664538527, 5664538445, 5664538528, 5664538446, 5664538447, 1850042684, 5664538448, 5664538449, 5664538450, 5664538529, 5664538451, 5664538452, 5664538453, 5664538530, 5664538531, 4609152308, 4609152306, 4609152303, 4609152299, 4609152297, 4609148885, 4609152289, 4609152291, 4609152294], "tags": {"name": "Butterfly Farm And Ski Garden", "source": "NSW LPI Base Map", "source:date": "2016-08", "tourism": "attraction", "website": "http://www.butterflyfarm.com.au/"}}]}